maxlib/__init__.py
maxlib/classes.py
maxlib/errors.py
maxlib/filters.py
maxlib/max.py
maxlib-0.1b1.dist-info/licenses/LICENSE
maxlib-0.1b1.dist-info/METADATA
maxlib-0.1b1.dist-info/WHEEL
maxlib-0.1b1.dist-info/top_level.txt
maxlib-0.1b1.dist-info/RECORD
