Metadata-Version: 2.4
Name: maxlib
Version: 0.1b1
Summary: A utility library containing classes, errors, filters, and max functions
Home-page: https://github.com/xNoBanOnlyZXC/WebMaxLib
Author: Sudo
Author-email: sudo@onlysq.ru
Classifier: Programming Language :: Python :: 3
Classifier: License :: OSI Approved :: GNU General Public License v3 (GPLv3)
Classifier: Operating System :: OS Independent
Requires-Python: >=3.6
License-File: LICENSE
Requires-Dist: websockets
Requires-Dist: requests
Dynamic: author
Dynamic: author-email
Dynamic: classifier
Dynamic: description
Dynamic: description-content-type
Dynamic: home-page
Dynamic: license-file
Dynamic: requires-dist
Dynamic: requires-python
Dynamic: summary
